{
    "o!_bagno": [
        {
            "file": "bagno.0.mp3",
            "performer": null,
            "source": "https://www.youtube.com/watch?v=7BJZaNN_Sl0"
        }
    ],

    "o!_ballada_o_dziewczynie_co_pila_gorace@mleko_zielen": [
        {
            "file": "ballada_o_dziewczynie_co_pila_gorace_mleko.michal_zielen.mp3",
            "performer": "Michał Zieleń",
            "source": "https://www.youtube.com/watch?v=IGA0v6mqAd0"
        }
    ],

    "o!_ballada_o_morzu@hania_czajkowska": [
        {
            "file": "ballada_o_morzu.hania_czajkowska.mp3",
            "performer": "Hania Czajkowska",
            "source": "https://www.youtube.com/watch?v=gr78WI3KWdU"
        }
    ],

    "o!_bo_mi_sie_gory_kojarza_z_chlopakiem": [
        {
            "file": "bo_mi_sie_gory_kojarza_z_chlopakiem.szczep_144_wdhigz.mp3",
            "performer": "Szczep 144 WDHiGZ"
        }
    ],

    "o!_czas": [
        {
            "file": "czas.0.mp3",
            "performer": null
        }
    ],

    "o!_dlonie_plecione": [
        {
            "file": "dlonie_plecione.0.mp3",
            "performer": null,
            "source": "https://www.youtube.com/watch?v=-33hi1R9Qao"
        }
    ],

    "o!_epitafium_dla_majora_ognia": [
        {
            "file": "epitafium_dla_majora_ognia.andrzej_kolakowski.mp3",
            "performer": "Andrzej Kołakowski",
            "source": "https://www.youtube.com/watch?v=t1InFE0SD-Q"
        }
    ],

    "o!_gwiazdy": [
        {
            "file": "gwiazdy.wiktoria_cwik.mp3",
            "performer": "Wiktoria Ćwik",
            "source": "https://www.youtube.com/watch?v=cmONy6PqNzU"
        }
    ],

    "o!_jam": [
        {
            "file": "jam.jaaamw-u.mp3",
            "performer": "JAAAMW-u",
            "source": "https://www.youtube.com/watch?v=AYUiPd3Gd8E"
        }
    ],

    "o!_lubie_mowic_z_toba": [
        {
            "file": "lubie_mowic_z_toba.tuiteraz2.mp3",
            "performer": "@tuiteraz2",
            "source": "https://www.youtube.com/watch?v=qQbiT8hLI8Q"
        }
    ],

    "o!_major_ponury": [
        {
            "file": "major_ponury.jaaamw-u.mp3",
            "performer": "JAAAMW-u",
            "source": "https://www.youtube.com/watch?v=7T9_iSooTWQ"
        }
    ],

    "o!_ostatnia_kula": [
        {
            "file": "ostatnia_kula.sebastian_bialecki.mp3",
            "performer": "Sebastian Białecki",
            "source": "https://www.youtube.com/watch?v=edXRpknX4rw"
        }
    ],

    "o!_piesn_xxix": [
        {
            "file": "piesn_xxix.tuiteraz2.mp3",
            "performer": "@tuiteraz2",
            "source": "https://www.youtube.com/watch?v=CAdq5pKWCOo"
        }
    ],

    "o!_plonie_ognisko": [
        {
            "file": "plonie_ognisko.0.mp3",
            "performer": null,
            "source": "https://www.youtube.com/watch?v=ArwHEekmxtw"
        }
    ],

    "o!_poezja": [
        {
            "file": "poezja.tuiteraz2.mp3",
            "performer": "@tuiteraz2",
            "source": "https://www.youtube.com/watch?v=CAdq5pKWCOo"
        }
    ],

    "o!_powrocisz_znow": [
        {
            "file": "powrocisz_znow.mania_zalotynska.mp3",
            "performer": "Mania Zalotyńska",
            "source": "https://www.youtube.com/watch?v=j6TcZflX1Cg"
        }
    ],

    "o!_pozytywka": [
        {
            "file": "pozytywka.szymon_zychowicz.mp3",
            "performer": "Szymon Zychowicz",
            "source": "https://www.youtube.com/watch?v=5bnR81Tm0qk"
        }
    ],

    "o!_testament_moj": [
        {
            "file": "testament_moj.moja_ojczyzna.mp3",
            "performer": "Moja Ojczyzna",
            "source": "https://www.youtube.com/watch?v=Ste0I9KBtOE"
        }
    ],

    "o!_twoj_krzyz": [
        {
            "file": "twoj_krzyz.wspolnota_milosci_ukrzyzowanej.mp3",
            "performer": "Wspólnota Miłości Ukrzyżowanej"
        }
    ],

    "o!_wiatr_chcial_zgasic": [
        {
            "file": "wiatr_chcial_zgasic.mostowy88.mp3",
            "performer": "@mostowy88"
        }
    ],

    "o!_wiklina": [
        {
            "file": "wiklina.0.mp3",
            "performer": null
        }
    ]



}
